modulenv/__init__.py
modulenv/commands.py
modulenv/environment.py
modulenv/files.py
modulenv/module.py
modulenv/sources.py
modulenv/templates.py
modulenv/utils.py
modulenv-0.0.6.data/scripts/meconf
modulenv-0.0.6.data/scripts/menv
modulenv-0.0.6.dist-info/DESCRIPTION.rst
modulenv-0.0.6.dist-info/METADATA
modulenv-0.0.6.dist-info/RECORD
modulenv-0.0.6.dist-info/WHEEL
modulenv-0.0.6.dist-info/metadata.json
modulenv-0.0.6.dist-info/top_level.txt
