Metadata-Version: 2.0
Name: modulenv
Version: 0.0.6
Summary: Module software environment configuration tools
Home-page: https://github.com/setempler/modulenv
Author: Sven E. Templer
Author-email: sven.templer@gmail.com
License: MIT
Keywords: module,software,environment
Platform: UNKNOWN
Classifier: License :: OSI Approved :: MIT License
